photonai/__init__.py
photonai/requirements.txt
photonai/version.py
photonai/base/__init__.py
photonai/base/cache_manager.py
photonai/base/hyperpipe.py
photonai/base/json_transformer.py
photonai/base/model_zoo.py
photonai/base/naming.py
photonai/base/photon_elements.py
photonai/base/photon_pipeline.py
photonai/base/registry/PhotonCore.json
photonai/base/registry/__init__.py
photonai/base/registry/registry.py
photonai/base/registry/modules/__init__.py
photonai/helper/__init__.py
photonai/helper/dummy_elements.py
photonai/helper/helper.py
photonai/helper/photon_base_test.py
photonai/modelwrapper/OrdinalEncoder.py
photonai/modelwrapper/PhotonMLPClassifier.py
photonai/modelwrapper/PhotonOneClassSVM.py
photonai/modelwrapper/RangeRestrictor.py
photonai/modelwrapper/SamplePairing.py
photonai/modelwrapper/Voting.py
photonai/modelwrapper/__init__.py
photonai/modelwrapper/base_model_wrapper.py
photonai/modelwrapper/confounder_removal.py
photonai/modelwrapper/cpm_feature_selection.py
photonai/modelwrapper/feature_selection.py
photonai/modelwrapper/imbalanced_data_transformer.py
photonai/modelwrapper/keras_base_estimator.py
photonai/modelwrapper/keras_base_models.py
photonai/modelwrapper/keras_dnn_classifier.py
photonai/modelwrapper/keras_dnn_regressor.py
photonai/modelwrapper/label_encoder.py
photonai/modelwrapper/source_splitter.py
photonai/optimization/__init__.py
photonai/optimization/base_optimizer.py
photonai/optimization/config_grid.py
photonai/optimization/hyperparameters.py
photonai/optimization/optimization_info.py
photonai/optimization/performance_constraints.py
photonai/optimization/grid_search/__init__.py
photonai/optimization/grid_search/grid_search.py
photonai/optimization/nevergrad/__init__.py
photonai/optimization/nevergrad/nevergrad.py
photonai/optimization/nevergrad/requirements.txt
photonai/optimization/random_search/__init__.py
photonai/optimization/random_search/random_search.py
photonai/optimization/scikit_optimize/__init__.py
photonai-2.5.2.dist-info/AUTHORS
photonai-2.5.2.dist-info/LICENSE
photonai-2.5.2.dist-info/METADATA
photonai-2.5.2.dist-info/WHEEL
photonai-2.5.2.dist-info/pbr.json
photonai-2.5.2.dist-info/top_level.txt
photonai-2.5.2.dist-info/RECORD
