Metadata-Version: 2.1
Name: photonai
Version: 2.5.2
Summary: PHOTONAI is a high level python API for designing and optimizing machine learning pipelines.
Home-page: https://www.photon-ai.com/
Download-URL: https://pypi.org/project/photonai/#files
Author: PHOTONAI Team
Author-email: hahnt@wwu.de
License: GPLv3
Project-URL: Source Code, https://github.com/wwu-mmll/photonai/
Project-URL: Documentation, https://wwu-mmll.github.io/photonai/
Project-URL: Bug Tracker, https://github.com/wwu-mmll/photonai/issues
Keywords: machine learning,pipeline,research,hyperparameter,hyperparameter optimization
Classifier: Programming Language :: Python :: 3
Classifier: License :: OSI Approved :: GNU General Public License v3 (GPLv3)
Classifier: Operating System :: OS Independent
Classifier: Intended Audience :: Science/Research
Classifier: Intended Audience :: Developers
License-File: LICENSE
License-File: AUTHORS
Requires-Dist: numpy
Requires-Dist: matplotlib
Requires-Dist: scikit-learn==1.5.2
Requires-Dist: pandas
Requires-Dist: plotly
Requires-Dist: imbalanced-learn==0.12.4
Requires-Dist: pymodm
Requires-Dist: scipy
Requires-Dist: statsmodels
Requires-Dist: prettytable
Requires-Dist: seaborn
Requires-Dist: joblib
Requires-Dist: dask>=2021.10.0
Requires-Dist: distributed
Requires-Dist: scikit-optimize
Requires-Dist: xlrd
Requires-Dist: pbr
